hicumL2V2p4p0_vae-0.7.5.dist-info/METADATA
hicumL2V2p4p0_vae-0.7.5.dist-info/WHEEL
hicumL2V2p4p0_vae.abi3.so
hicumL2V2p4p0_vae-0.7.5.dist-info/RECORD
