Metadata-Version: 2.1
Name: hicumL2V2p4p0_vae
Version: 0.7.5
Summary: A python package generated by VerilogAE
Author: 
